piethon/__init__.py
piethon/stack.py
piethon-0.1.0.dist-info/LICENSE
piethon-0.1.0.dist-info/METADATA
piethon-0.1.0.dist-info/WHEEL
piethon-0.1.0.dist-info/RECORD
