Metadata-Version: 2.1
Name: piethon
Version: 0.1.0
Summary: A Python based Piet interpreter
License: MIT
Author: Alex James
Requires-Python: >=3.10,<4.0
Classifier: License :: OSI Approved :: MIT License
Classifier: Programming Language :: Python :: 3
Classifier: Programming Language :: Python :: 3.10
Classifier: Programming Language :: Python :: 3.11
